simpletap/__init__.py
simpletap/__main__.py
simpletap/result.py
simpletap/runner.py
simpletap/version.py
simpletap/tests/__init__.py
simpletap/tests/test_api.py
simpletap/tests/test_runner.py
simpletap-2.0.0.dist-info/LICENSE
simpletap-2.0.0.dist-info/METADATA
simpletap-2.0.0.dist-info/WHEEL
simpletap-2.0.0.dist-info/top_level.txt
simpletap-2.0.0.dist-info/RECORD
