Metadata-Version: 2.1
Name: simpletap
Version: 2.0.0
Summary: Unittest runner producing Test Anything Protocol (TAP) output
Home-page: https://github.com/Unode/simpletap
Author: Renato Alves
Author-email: alves.rjc@gmail.com
Maintainer: Renato Alves
License: MIT
Platform: any
Classifier: Development Status :: 5 - Production/Stable
Classifier: Intended Audience :: Developers
Classifier: License :: OSI Approved :: MIT License
Classifier: Operating System :: OS Independent
Classifier: Programming Language :: Python :: 2
Classifier: Programming Language :: Python :: 3
Classifier: Topic :: Scientific/Engineering :: Interface Engine/Protocol Translator
Classifier: Topic :: Software Development :: Testing
Classifier: Topic :: Software Development :: Libraries :: Python Modules
